gibberish/__init__.py
gibberish/dir.py
gibberish/database/components.yaml
gibberish/database/raw_components.yaml
gibberish-0.4.0.dist-info/LICENSE.txt
gibberish-0.4.0.dist-info/METADATA
gibberish-0.4.0.dist-info/WHEEL
gibberish-0.4.0.dist-info/entry_points.txt
gibberish-0.4.0.dist-info/top_level.txt
gibberish-0.4.0.dist-info/RECORD
