Metadata-Version: 2.1
Name: gibberish
Version: 0.4.0
Summary: A pseudo-word generator
Home-page: https://github.com/greghaskins/gibberish
Author: Gregory Haskins
Author-email: greg@greghaskins.com
License: MIT License
Platform: UNKNOWN
Classifier: Intended Audience :: Developers
Classifier: License :: OSI Approved :: MIT License
Classifier: Natural Language :: English
Classifier: Programming Language :: Python :: 2
Classifier: Programming Language :: Python :: 3
Provides-Extra: dev
